databricks_aws_utils/__init__.py
databricks_aws_utils/delta_table.py
databricks_aws_utils/rds.py
databricks_aws_utils/s3.py
databricks_aws_utils/session.py
databricks_aws_utils-1.6.0.dist-info/METADATA
databricks_aws_utils-1.6.0.dist-info/WHEEL
databricks_aws_utils-1.6.0.dist-info/licenses/LICENSE
databricks_aws_utils-1.6.0.dist-info/RECORD
