Metadata-Version: 2.4
Name: databricks-aws-utils
Version: 1.6.0
Summary: Databricks AWS Utils
License: Proprietary
License-File: LICENSE
Author: Lucas Vieira
Author-email: lucas.vieira94@outlook.com
Maintainer: Lucas Vieira
Maintainer-email: lucas.vieira94@outlook.com
Requires-Python: >=3.8.1,<=3.14
Classifier: License :: Other/Proprietary License
Classifier: Programming Language :: Python :: 3
Classifier: Programming Language :: Python :: 3.9
Classifier: Programming Language :: Python :: 3.10
Classifier: Programming Language :: Python :: 3.11
Classifier: Programming Language :: Python :: 3.12
Classifier: Programming Language :: Python :: 3.13
Classifier: Programming Language :: Python :: 3.14
Project-URL: Repository, https://github.com/lucasvieirasilva/databricks-aws-utils
